README.md
setup.py
geoshaper/__init__.py
geoshaper.egg-info/PKG-INFO
geoshaper.egg-info/SOURCES.txt
geoshaper.egg-info/dependency_links.txt
geoshaper.egg-info/requires.txt
geoshaper.egg-info/top_level.txt
geoshaper.egg-info/zip-safe